Users/alin/.config/flimdb/config.toml
flimdb/__init__.py
flimdb/filelist.py
flimdb/flimdb.py
flimdb/movielib.py
flimdb/torrentlib.py
flimdb/config/config.toml
tests/__init__.py
flimdb-2.1.1.dist-info/LICENSE-APACHE
flimdb-2.1.1.dist-info/LICENSE-MIT
flimdb-2.1.1.dist-info/METADATA
flimdb-2.1.1.dist-info/WHEEL
flimdb-2.1.1.dist-info/entry_points.txt
flimdb-2.1.1.dist-info/top_level.txt
flimdb-2.1.1.dist-info/RECORD
